satellite_images_nso/__init__.py
satellite_images_nso/__blob_storage/__init__.py
satellite_images_nso/__blob_storage/blob_storage.py
satellite_images_nso/__lidar/__init__.py
satellite_images_nso/__lidar/ahn.py
satellite_images_nso/__normalisation/__init__.py
satellite_images_nso/__normalisation/normalisation.py
satellite_images_nso/__normalisation/coefficients/__init__.py
satellite_images_nso/_manipulation/__init__.py
satellite_images_nso/_manipulation/nso_manipulator.py
satellite_images_nso/_nso_data_extraction/__init__.py
satellite_images_nso/_nso_data_extraction/nso_api.py
satellite_images_nso/_nvdi/__init__.py
satellite_images_nso/_nvdi/calculate_nvdi.py
satellite_images_nso/api/__init__.py
satellite_images_nso/api/nso_georegion.py
satellite_images_nso/api/sat_manipulator.py
satellite_images_nso/miscellaneous/__init__.py
satellite_images_nso/miscellaneous/miscellaneous.py
scheduling/__init__.py
scheduling/coepelduynen/__init__.py
scheduling/coepelduynen/coepelduynen_schedule_SV_50cm_RGBI.py
satellite_images_nso-1.2.5.dist-info/LICENSE
satellite_images_nso-1.2.5.dist-info/METADATA
satellite_images_nso-1.2.5.dist-info/WHEEL
satellite_images_nso-1.2.5.dist-info/top_level.txt
satellite_images_nso-1.2.5.dist-info/RECORD
