Metadata-Version: 2.1
Name: satellite-images-nso
Version: 1.2.5
Summary: NSO Satellite Extractor and cropper
Home-page: https://github.com/ProvZH/satellite_images_nso
Author: Michael de Winter
Author-email: m.r.dewinter88@live.nl
Classifier: Programming Language :: Python :: 3
Classifier: License :: OSI Approved :: MIT License
Classifier: Operating System :: OS Independent
Requires-Python: >=3.6
License-File: LICENSE
Requires-Dist: requests (>=2.25.0)
Requires-Dist: objectpath (>=0.6.1)
Requires-Dist: earthpy (>=0.9.2)
Requires-Dist: Fiona (>=1.8.13)
Requires-Dist: GDAL (>=3.0.4)
Requires-Dist: geopandas (>=0.7.0)
Requires-Dist: rasterio (>=1.1.3)
Requires-Dist: Shapely (>=1.7.0)
